mechasvg/__init__.py
mechasvg/__main__.py
mechasvg/supl/__init__.py
mechaSVG-0.1.1.post1.dist-info/LICENSE.txt
mechaSVG-0.1.1.post1.dist-info/METADATA
mechaSVG-0.1.1.post1.dist-info/WHEEL
mechaSVG-0.1.1.post1.dist-info/top_level.txt
mechaSVG-0.1.1.post1.dist-info/RECORD
