Metadata-Version: 2.1
Name: mechaSVG
Version: 0.1.1.post1
Summary: mechaSVG is a python & tk application for creating good-looking energy profile diagrams as Scalable Vector Graphics.
Home-page: https://github.com/ricalmang/mechaSVG
Author: Ricardo Almir Angnes
Author-email: ricardo_almir@hotmail.com
License: MIT
Keywords: chemistry
Platform: UNKNOWN
Classifier: Programming Language :: Python :: 3
Classifier: License :: OSI Approved :: MIT License
Classifier: Operating System :: OS Independent
Requires-Python: >=3.6
Requires-Dist: openpyxl
